edfrd/__init__.py
edfrd-0.7.dist-info/entry_points.txt
edfrd-0.7.dist-info/LICENSE
edfrd-0.7.dist-info/WHEEL
edfrd-0.7.dist-info/METADATA
edfrd-0.7.dist-info/RECORD
