Metadata-Version: 2.1
Name: edfrd
Version: 0.7
Summary: edfrd is a Python 3 software library to read and write EDF files.
Home-page: https://cbmi.htw-berlin.de/
License: LGPL-3.0
Author: Christoph Jansen
Author-email: Christoph.Jansen@htw-berlin.de
Requires-Python: >=3.4,<4.0
Classifier: License :: OSI Approved :: GNU Lesser General Public License v3 (LGPLv3)
Classifier: Programming Language :: Python :: 3
Classifier: Programming Language :: Python :: 3.4
Classifier: Programming Language :: Python :: 3.5
Classifier: Programming Language :: Python :: 3.6
Classifier: Programming Language :: Python :: 3.7
Requires-Dist: numpy (>=1.15,<2.0)
Project-URL: Repository, https://github.com/somnonetz/edfrd
